{
  "_fv": 18,
  "_type": "gun",
  "definition": {
    "renderType": 0,
    "texture": "image-removebg-preview",
    "customModelName": "Normal",
    "name": "Gun",
    "specialInfo": [],
    "creativeTab": {
      "value": "CUSTOM:Mod"
    },
    "stackSize": 1,
    "ammoItem": {
      "value": "Items.REDSTONE"
    },
    "shootConstantly": true,
    "usageCount": 9000,
    "actionSound": {
      "value": "entity.arrow.shoot"
    },
    "hasGlow": false,
    "animation": "none",
    "enableMeleeDamage": true,
    "damageVsEntity": 4.0,
    "bulletPower": 9.0,
    "bulletDamage": 5.0,
    "bulletKnockback": 0,
    "bulletParticles": true,
    "bulletIgnitesFire": false,
    "bulletItemTexture": {
      "value": "Items.IRON_NUGGET"
    },
    "bulletModel": "Default",
    "customBulletModelTexture": ""
  }
}